{
  "protocol_version" : "0.0.5",
  "configuration" : {
    "version" : "(6.6.0.155) (2019-08/296a9afdb24)",
    "tlc" : "normal",
    "sigsgev" : "altstack",
    "notifications" : "kqueue",
    "architecture" : "amd64",
    "disabled_features" : "none",
    "smallconfig" : "disabled",
    "bigarrays" : "disabled",
    "softdebug" : "enabled",
    "interpreter" : "enabled",
    "llvm_support" : "0",
    "suspend" : "hybrid"
  },
  "memory" : {
    "Resident Size" : "40534016",
    "Virtual Size" : "4671008768",
    "minor_gc_time" : "825891",
    "major_gc_time" : "0",
    "minor_gc_count" : "2",
    "major_gc_count" : "0",
    "major_gc_time_concurrent" : "0"
 },
  "threads" : [
 {
    "is_managed" : true,
    "offset_free_hash" : "0x115869ea88",
    "offset_rich_hash" : "0x115869ee42",
    "crashed" : true,
    "native_thread_id" : "0x700003792000",
    "thread_info_addr" : "0x7f8e8890b000",
    "thread_name" : "Thread Pool Worker",
    "ctx" : {
      "IP" : "0x7fff64e6c7fa",
      "SP" : "0x7000037905e8",
      "BP" : "0x700003790610"
  },
    "managed_frames" : [
  {
      "is_managed" : "false",
      "native_address" : "unregistered"
   }
,
  {
      "is_managed" : "true",
      "guid" : "7D0BC631-CADD-4A07-BF74-717847E90CFA",
      "token" : "0x00000",
      "native_offset" : "0x0",
      "filename" : "mscorlib.dll",
      "sizeofimage" : "0x472000",
      "timestamp" : "0xec216ac8",
      "il_offset" : "0x0000c"
   }
,
  {
      "is_managed" : "true",
      "guid" : "7D0BC631-CADD-4A07-BF74-717847E90CFA",
      "token" : "0x6001f80",
      "native_offset" : "0x0",
      "filename" : "mscorlib.dll",
      "sizeofimage" : "0x472000",
      "timestamp" : "0xec216ac8",
      "il_offset" : "0x0001a"
   }
,
  {
      "is_managed" : "true",
      "guid" : "7D0BC631-CADD-4A07-BF74-717847E90CFA",
      "token" : "0x6001f27",
      "native_offset" : "0x0",
      "filename" : "mscorlib.dll",
      "sizeofimage" : "0x472000",
      "timestamp" : "0xec216ac8",
      "il_offset" : "0x00028"
   }
,
  {
      "is_managed" : "true",
      "guid" : "7D0BC631-CADD-4A07-BF74-717847E90CFA",
      "token" : "0x6001f25",
      "native_offset" : "0x0",
      "filename" : "mscorlib.dll",
      "sizeofimage" : "0x472000",
      "timestamp" : "0xec216ac8",
      "il_offset" : "0x00002"
   }
,
  {
      "is_managed" : "true",
      "guid" : "43D52422-E26B-4147-B4BC-462FF72EC4B3",
      "token" : "0x6000084",
      "native_offset" : "0x0",
      "filename" : "MonoDevelop.MSBuildBuilder.exe",
      "sizeofimage" : "0x14000",
      "timestamp" : "0x9323f5d4",
      "il_offset" : "0x000ae"
   }
,
  {
      "is_managed" : "true",
      "guid" : "43D52422-E26B-4147-B4BC-462FF72EC4B3",
      "token" : "0x6000083",
      "native_offset" : "0x0",
      "filename" : "MonoDevelop.MSBuildBuilder.exe",
      "sizeofimage" : "0x14000",
      "timestamp" : "0x9323f5d4",
      "il_offset" : "0x00001"
   }
,
  {
      "is_managed" : "true",
      "guid" : "43D52422-E26B-4147-B4BC-462FF72EC4B3",
      "token" : "0x600006a",
      "native_offset" : "0x0",
      "filename" : "MonoDevelop.MSBuildBuilder.exe",
      "sizeofimage" : "0x14000",
      "timestamp" : "0x9323f5d4",
      "il_offset" : "0x00048"
   }
,
  {
      "is_managed" : "true",
      "guid" : "43D52422-E26B-4147-B4BC-462FF72EC4B3",
      "token" : "0x60000a1",
      "native_offset" : "0x0",
      "filename" : "MonoDevelop.MSBuildBuilder.exe",
      "sizeofimage" : "0x14000",
      "timestamp" : "0x9323f5d4",
      "il_offset" : "0x00001"
   }
,
  {
      "is_managed" : "true",
      "guid" : "43D52422-E26B-4147-B4BC-462FF72EC4B3",
      "token" : "0x6000067",
      "native_offset" : "0x0",
      "filename" : "MonoDevelop.MSBuildBuilder.exe",
      "sizeofimage" : "0x14000",
      "timestamp" : "0x9323f5d4",
      "il_offset" : "0x00001"
   }
,
  {
      "is_managed" : "true",
      "guid" : "43D52422-E26B-4147-B4BC-462FF72EC4B3",
      "token" : "0x6000075",
      "native_offset" : "0x0",
      "filename" : "MonoDevelop.MSBuildBuilder.exe",
      "sizeofimage" : "0x14000",
      "timestamp" : "0x9323f5d4",
      "il_offset" : "0x00057"
   }
,
  {
      "is_managed" : "true",
      "guid" : "43D52422-E26B-4147-B4BC-462FF72EC4B3",
      "token" : "0x00000",
      "native_offset" : "0x0",
      "filename" : "MonoDevelop.MSBuildBuilder.exe",
      "sizeofimage" : "0x14000",
      "timestamp" : "0x9323f5d4",
      "il_offset" : "0x0002a"
   }
,
  {
      "is_managed" : "false",
      "native_address" : "unregistered"
   }
,
  {
      "is_managed" : "true",
      "guid" : "7D0BC631-CADD-4A07-BF74-717847E90CFA",
      "token" : "0x00000",
      "native_offset" : "0x0",
      "filename" : "mscorlib.dll",
      "sizeofimage" : "0x472000",
      "timestamp" : "0xec216ac8",
      "il_offset" : "0x0000c"
   }
,
  {
      "is_managed" : "true",
      "guid" : "7D0BC631-CADD-4A07-BF74-717847E90CFA",
      "token" : "0x6004cdb",
      "native_offset" : "0x0",
      "filename" : "mscorlib.dll",
      "sizeofimage" : "0x472000",
      "timestamp" : "0xec216ac8",
      "il_offset" : "0x0006a"
   }
,
  {
      "is_managed" : "true",
      "guid" : "7D0BC631-CADD-4A07-BF74-717847E90CFA",
      "token" : "0x60048c4",
      "native_offset" : "0x0",
      "filename" : "mscorlib.dll",
      "sizeofimage" : "0x472000",
      "timestamp" : "0xec216ac8",
      "il_offset" : "0x00000"
   }
,
  {
      "is_managed" : "true",
      "guid" : "43D52422-E26B-4147-B4BC-462FF72EC4B3",
      "token" : "0x6000039",
      "native_offset" : "0x0",
      "filename" : "MonoDevelop.MSBuildBuilder.exe",
      "sizeofimage" : "0x14000",
      "timestamp" : "0x9323f5d4",
      "il_offset" : "0x00019"
   }
,
  {
      "is_managed" : "true",
      "guid" : "43D52422-E26B-4147-B4BC-462FF72EC4B3",
      "token" : "0x6000166",
      "native_offset" : "0x0",
      "filename" : "MonoDevelop.MSBuildBuilder.exe",
      "sizeofimage" : "0x14000",
      "timestamp" : "0x9323f5d4",
      "il_offset" : "0x00029"
   }
,
  {
      "is_managed" : "true",
      "guid" : "43D52422-E26B-4147-B4BC-462FF72EC4B3",
      "token" : "0x6000181",
      "native_offset" : "0x0",
      "filename" : "MonoDevelop.MSBuildBuilder.exe",
      "sizeofimage" : "0x14000",
      "timestamp" : "0x9323f5d4",
      "il_offset" : "0x00001"
   }
,
  {
      "is_managed" : "true",
      "guid" : "7D0BC631-CADD-4A07-BF74-717847E90CFA",
      "token" : "0x6001fe8",
      "native_offset" : "0x0",
      "filename" : "mscorlib.dll",
      "sizeofimage" : "0x472000",
      "timestamp" : "0xec216ac8",
      "il_offset" : "0x00007"
   }
,
  {
      "is_managed" : "true",
      "guid" : "7D0BC631-CADD-4A07-BF74-717847E90CFA",
      "token" : "0x6001ec3",
      "native_offset" : "0x0",
      "filename" : "mscorlib.dll",
      "sizeofimage" : "0x472000",
      "timestamp" : "0xec216ac8",
      "il_offset" : "0x00071"
   }
,
  {
      "is_managed" : "true",
      "guid" : "7D0BC631-CADD-4A07-BF74-717847E90CFA",
      "token" : "0x6001ec1",
      "native_offset" : "0x0",
      "filename" : "mscorlib.dll",
      "sizeofimage" : "0x472000",
      "timestamp" : "0xec216ac8",
      "il_offset" : "0x00000"
   }
,
  {
      "is_managed" : "true",
      "guid" : "7D0BC631-CADD-4A07-BF74-717847E90CFA",
      "token" : "0x6001fe6",
      "native_offset" : "0x0",
      "filename" : "mscorlib.dll",
      "sizeofimage" : "0x472000",
      "timestamp" : "0xec216ac8",
      "il_offset" : "0x00021"
   }
,
  {
      "is_managed" : "true",
      "guid" : "7D0BC631-CADD-4A07-BF74-717847E90CFA",
      "token" : "0x6001fce",
      "native_offset" : "0x0",
      "filename" : "mscorlib.dll",
      "sizeofimage" : "0x472000",
      "timestamp" : "0xec216ac8",
      "il_offset" : "0x00074"
   }
,
  {
      "is_managed" : "true",
      "guid" : "7D0BC631-CADD-4A07-BF74-717847E90CFA",
      "token" : "0x6001fe3",
      "native_offset" : "0x0",
      "filename" : "mscorlib.dll",
      "sizeofimage" : "0x472000",
      "timestamp" : "0xec216ac8",
      "il_offset" : "0x00000"
   }
,
  {
      "is_managed" : "true",
      "guid" : "7D0BC631-CADD-4A07-BF74-717847E90CFA",
      "token" : "0x00000",
      "native_offset" : "0x0",
      "filename" : "mscorlib.dll",
      "sizeofimage" : "0x472000",
      "timestamp" : "0xec216ac8",
      "il_offset" : "0x0002a"
   }

  ],
  "unmanaged_frames" : [
 {
    "is_managed" : "false",
    "native_address" : "0x101c63156",
    "native_offset" : "0x00000"
  }
,
 {
    "is_managed" : "false",
    "native_address" : "0x101e09775",
    "native_offset" : "0x00000"
  }
,
 {
    "is_managed" : "false",
    "native_address" : "0x101e09dfa",
    "native_offset" : "0x00000"
  }
,
 {
    "is_managed" : "false",
    "native_address" : "0x101ccef46",
    "native_offset" : "0x00000"
  }
,
 {
    "is_managed" : "false",
    "native_address" : "0x101c67c65",
    "native_offset" : "0x00000"
  }
,
 {
    "is_managed" : "false",
    "native_address" : "0x101cce2db",
    "native_offset" : "0x00000"
  }
,
 {
    "is_managed" : "false",
    "native_address" : "0x7fff64f2342d",
    "native_offset" : "0x00000"
  }
,
 {
    "is_managed" : "false",
    "native_address" : "unregistered"
  }
,
 {
    "is_managed" : "false",
    "native_address" : "0x7fff64df3a1c",
    "native_offset" : "0x00000"
  }
,
 {
    "is_managed" : "false",
    "native_address" : "0x101ed8cb7",
    "native_offset" : "0x00000"
  }
,
 {
    "is_managed" : "false",
    "native_address" : "0x101eb9b2f",
    "native_offset" : "0x00000"
  }
,
 {
    "is_managed" : "false",
    "native_address" : "0x101ed903e",
    "native_offset" : "0x00000"
  }
,
 {
    "is_managed" : "false",
    "native_address" : "0x101ed91bf",
    "native_offset" : "0x00000"
  }
,
 {
    "is_managed" : "false",
    "native_address" : "0x101d73e76",
    "native_offset" : "0x00000"
  }
,
 {
    "is_managed" : "false",
    "native_address" : "0x101d74478",
    "native_offset" : "0x00000"
  }
,
 {
    "is_managed" : "false",
    "native_address" : "0x101ec719f",
    "native_offset" : "0x00000"
  }
,
 {
    "is_managed" : "false",
    "native_address" : "0x101ec74b0",
    "native_offset" : "0x00000"
  }
,
 {
    "is_managed" : "false",
    "native_address" : "0x101d767ab",
    "native_offset" : "0x00000"
  }
,
 {
    "is_managed" : "false",
    "native_address" : "0x101d99675",
    "native_offset" : "0x00000"
  }
,
 {
    "is_managed" : "true",
    "guid" : "7D0BC631-CADD-4A07-BF74-717847E90CFA",
    "token" : "0x00000",
    "native_offset" : "0x0",
    "filename" : "mscorlib.dll",
    "sizeofimage" : "0x472000",
    "timestamp" : "0xec216ac8",
    "il_offset" : "0x00000"
  }
,
 {
    "is_managed" : "true",
    "guid" : "43D52422-E26B-4147-B4BC-462FF72EC4B3",
    "token" : "0x6000083",
    "native_offset" : "0x0",
    "filename" : "MonoDevelop.MSBuildBuilder.exe",
    "sizeofimage" : "0x14000",
    "timestamp" : "0x9323f5d4",
    "il_offset" : "0x00000"
  }
,
 {
    "is_managed" : "true",
    "guid" : "43D52422-E26B-4147-B4BC-462FF72EC4B3",
    "token" : "0x60000a1",
    "native_offset" : "0x0",
    "filename" : "MonoDevelop.MSBuildBuilder.exe",
    "sizeofimage" : "0x14000",
    "timestamp" : "0x9323f5d4",
    "il_offset" : "0x00000"
  }
,
 {
    "is_managed" : "true",
    "guid" : "43D52422-E26B-4147-B4BC-462FF72EC4B3",
    "token" : "0x00000",
    "native_offset" : "0x0",
    "filename" : "MonoDevelop.MSBuildBuilder.exe",
    "sizeofimage" : "0x14000",
    "timestamp" : "0x9323f5d4",
    "il_offset" : "0x00000"
  }
,
 {
    "is_managed" : "false",
    "native_address" : "0x101bc362d",
    "native_offset" : "0x00000"
  }
,
 {
    "is_managed" : "false",
    "native_address" : "0x101de2fa4",
    "native_offset" : "0x00000"
  }
,
 {
    "is_managed" : "false",
    "native_address" : "0x101de73a6",
    "native_offset" : "0x00000"
  }
,
 {
    "is_managed" : "false",
    "native_address" : "0x101d7e6f4",
    "native_offset" : "0x00000"
  }
,
 {
    "is_managed" : "true",
    "guid" : "7D0BC631-CADD-4A07-BF74-717847E90CFA",
    "token" : "0x00000",
    "native_offset" : "0x0",
    "filename" : "mscorlib.dll",
    "sizeofimage" : "0x472000",
    "timestamp" : "0xec216ac8",
    "il_offset" : "0x00000"
  }
,
 {
    "is_managed" : "true",
    "guid" : "7D0BC631-CADD-4A07-BF74-717847E90CFA",
    "token" : "0x60048c4",
    "native_offset" : "0x0",
    "filename" : "mscorlib.dll",
    "sizeofimage" : "0x472000",
    "timestamp" : "0xec216ac8",
    "il_offset" : "0x00000"
  }
,
 {
    "is_managed" : "true",
    "guid" : "43D52422-E26B-4147-B4BC-462FF72EC4B3",
    "token" : "0x6000181",
    "native_offset" : "0x0",
    "filename" : "MonoDevelop.MSBuildBuilder.exe",
    "sizeofimage" : "0x14000",
    "timestamp" : "0x9323f5d4",
    "il_offset" : "0x00000"
  }
,
 {
    "is_managed" : "true",
    "guid" : "7D0BC631-CADD-4A07-BF74-717847E90CFA",
    "token" : "0x6001ec1",
    "native_offset" : "0x0",
    "filename" : "mscorlib.dll",
    "sizeofimage" : "0x472000",
    "timestamp" : "0xec216ac8",
    "il_offset" : "0x00000"
  }
,
 {
    "is_managed" : "true",
    "guid" : "7D0BC631-CADD-4A07-BF74-717847E90CFA",
    "token" : "0x6001fe3",
    "native_offset" : "0x0",
    "filename" : "mscorlib.dll",
    "sizeofimage" : "0x472000",
    "timestamp" : "0xec216ac8",
    "il_offset" : "0x00000"
  }
,
 {
    "is_managed" : "false",
    "native_address" : "0x101bc362d",
    "native_offset" : "0x00000"
  }
,
 {
    "is_managed" : "false",
    "native_address" : "0x101de2fa4",
    "native_offset" : "0x00000"
  }
,
 {
    "is_managed" : "false",
    "native_address" : "0x101e0cec0",
    "native_offset" : "0x00000"
  }
,
 {
    "is_managed" : "false",
    "native_address" : "0x101d3f28c",
    "native_offset" : "0x00000"
  }
,
 {
    "is_managed" : "false",
    "native_address" : "0x101e0a373",
    "native_offset" : "0x00000"
  }
,
 {
    "is_managed" : "false",
    "native_address" : "0x7fff64f2ee65",
    "native_offset" : "0x00000"
  }
,
 {
    "is_managed" : "false",
    "native_address" : "0x7fff64f2a83b",
    "native_offset" : "0x00000"
  }

 ]
},
{
  "is_managed" : false,
  "offset_free_hash" : "0x0",
  "offset_rich_hash" : "0x0",
  "crashed" : false,
  "native_thread_id" : "0x700003083000",
  "thread_info_addr" : "0x7f8e85000400",
  "thread_name" : "Finalizer",
  "ctx" : {
    "IP" : "0x7fff64e66296",
    "SP" : "0x700003082e48",
    "BP" : "0x700003082ef0"
 },
  "unmanaged_frames" : [
 {
    "is_managed" : "false",
    "native_address" : "0x101c63156",
    "native_offset" : "0x00000"
  }
,
 {
    "is_managed" : "false",
    "native_address" : "0x101e09775",
    "native_offset" : "0x00000"
  }
,
 {
    "is_managed" : "false",
    "native_address" : "0x101e094a7",
    "native_offset" : "0x00000"
  }
,
 {
    "is_managed" : "false",
    "native_address" : "0x101ccdf3c",
    "native_offset" : "0x00000"
  }
,
 {
    "is_managed" : "false",
    "native_address" : "0x7fff64f2342d",
    "native_offset" : "0x00000"
  }
,
 {
    "is_managed" : "false",
    "native_address" : "0x100000000",
    "native_offset" : "0x00000"
  }
,
 {
    "is_managed" : "false",
    "native_address" : "0x101e0a373",
    "native_offset" : "0x00000"
  }
,
 {
    "is_managed" : "false",
    "native_address" : "0x7fff64f2ee65",
    "native_offset" : "0x00000"
  }
,
 {
    "is_managed" : "false",
    "native_address" : "0x7fff64f2a83b",
    "native_offset" : "0x00000"
  }

 ]
},
{
  "is_managed" : false,
  "offset_free_hash" : "0x0",
  "offset_rich_hash" : "0x0",
  "crashed" : false,
  "native_thread_id" : "0x11047ddc0",
  "thread_info_addr" : "0x7f8e86802000",
  "thread_name" : "tid_307",
  "ctx" : {
    "IP" : "0x7fff64e68ce6",
    "SP" : "0x7ffeee04fd08",
    "BP" : "0x7ffeee04fda0"
 },
  "unmanaged_frames" : [
 {
    "is_managed" : "false",
    "native_address" : "0x101c63156",
    "native_offset" : "0x00000"
  }
,
 {
    "is_managed" : "false",
    "native_address" : "0x101e09775",
    "native_offset" : "0x00000"
  }
,
 {
    "is_managed" : "false",
    "native_address" : "0x101e094a7",
    "native_offset" : "0x00000"
  }
,
 {
    "is_managed" : "false",
    "native_address" : "0x101ccdf3c",
    "native_offset" : "0x00000"
  }
,
 {
    "is_managed" : "false",
    "native_address" : "0x7fff64f2342d",
    "native_offset" : "0x00000"
  }
,
 {
    "is_managed" : "false",
    "native_address" : "0x7ffeee04f9f8",
    "native_offset" : "0x00000"
  }
,
 {
    "is_managed" : "false",
    "native_address" : "0x101eb37c0",
    "native_offset" : "0x00000"
  }
,
 {
    "is_managed" : "false",
    "native_address" : "0x101ece2e1",
    "native_offset" : "0x00000"
  }
,
 {
    "is_managed" : "false",
    "native_address" : "0x101e06774",
    "native_offset" : "0x00000"
  }
,
 {
    "is_managed" : "false",
    "native_address" : "0x101e0658a",
    "native_offset" : "0x00000"
  }
,
 {
    "is_managed" : "false",
    "native_address" : "0x101c286c2",
    "native_offset" : "0x00000"
  }
,
 {
    "is_managed" : "false",
    "native_address" : "0x101bb2848",
    "native_offset" : "0x00000"
  }
,
 {
    "is_managed" : "false",
    "native_address" : "0x7fff64d257fd",
    "native_offset" : "0x00000"
  }
,
 {
    "is_managed" : "false",
    "native_address" : "0x5",
    "native_offset" : "0x00000"
  }

 ]
}
]
}